vogel_video_analyzer/__init__.py
vogel_video_analyzer/__main__.py
vogel_video_analyzer/analyzer.py
vogel_video_analyzer/cli.py
vogel_video_analyzer/github_sync.py
vogel_video_analyzer/i18n.py
vogel_video_analyzer/issue_board.py
vogel_video_analyzer/issue_cli.py
vogel_video_analyzer/reporter.py
vogel_video_analyzer/species_classifier.py
vogel_video_analyzer-0.5.4.dist-info/licenses/LICENSE
vogel_video_analyzer-0.5.4.dist-info/METADATA
vogel_video_analyzer-0.5.4.dist-info/WHEEL
vogel_video_analyzer-0.5.4.dist-info/entry_points.txt
vogel_video_analyzer-0.5.4.dist-info/top_level.txt
vogel_video_analyzer-0.5.4.dist-info/RECORD
