Metadata-Version: 2.4
Name: vogel-video-analyzer
Version: 0.5.4
Summary: YOLOv8-based video analysis tool for automated bird content detection, quantification, and species identification
Author-email: kamera-linux <kamera-linux@mailbox.org>
License-Expression: MIT
Project-URL: Homepage, https://github.com/kamera-linux/vogel-video-analyzer
Project-URL: Documentation, https://github.com/kamera-linux/vogel-video-analyzer#readme
Project-URL: Repository, https://github.com/kamera-linux/vogel-video-analyzer
Project-URL: Issues, https://github.com/kamera-linux/vogel-video-analyzer/issues
Project-URL: Parent Project, https://github.com/kamera-linux/vogel-kamera-linux
Keywords: video,analysis,bird,detection,yolov8,opencv,computer-vision,wildlife,ornithology
Classifier: Development Status :: 4 - Beta
Classifier: Intended Audience :: Science/Research
Classifier: Intended Audience :: Developers
Classifier: Operating System :: OS Independent
Classifier: Programming Language :: Python :: 3
Classifier: Programming Language :: Python :: 3.8
Classifier: Programming Language :: Python :: 3.9
Classifier: Programming Language :: Python :: 3.10
Classifier: Programming Language :: Python :: 3.11
Classifier: Programming Language :: Python :: 3.12
Classifier: Programming Language :: Python :: 3.13
Classifier: Topic :: Multimedia :: Video
Classifier: Topic :: Scientific/Engineering :: Artificial Intelligence
Classifier: Topic :: Scientific/Engineering :: Image Recognition
Requires-Python: >=3.8
License-File: LICENSE
Requires-Dist: opencv-python>=4.8.0
Requires-Dist: ultralytics>=8.0.0
Requires-Dist: numpy>=1.24.0
Provides-Extra: dev
Requires-Dist: pytest>=7.0; extra == "dev"
Requires-Dist: pytest-cov>=4.0; extra == "dev"
Requires-Dist: black>=23.0; extra == "dev"
Requires-Dist: flake8>=6.0; extra == "dev"
Requires-Dist: mypy>=1.0; extra == "dev"
Provides-Extra: species
Requires-Dist: transformers>=4.30.0; extra == "species"
Requires-Dist: torch>=2.0.0; extra == "species"
Requires-Dist: torchvision>=0.15.0; extra == "species"
Requires-Dist: pillow>=10.0.0; extra == "species"
Provides-Extra: github
Requires-Dist: PyGithub>=2.1.0; extra == "github"
Dynamic: license-file
